river_core/__init__.py
river_core/constants.py
river_core/enquire.py
river_core/log.py
river_core/main.py
river_core/requirements.txt
river_core/rivercore.py
river_core/sim_hookspecs.py
river_core/utils.py
river_core/templates/coverage_report.html
river_core/templates/report.html
river_core/templates/style.css
river_core/templates/setup/dut/__init__.py
river_core/templates/setup/dut/conftest.py
river_core/templates/setup/dut/gen_framework.py
river_core/templates/setup/dut/sample_plugin.py
river_core/templates/setup/generator/__init__.py
river_core/templates/setup/generator/conftest.py
river_core/templates/setup/generator/gen_framework.py
river_core/templates/setup/generator/sample_plugin.py
river_core/templates/setup/reference/__init__.py
river_core/templates/setup/reference/conftest.py
river_core/templates/setup/reference/gen_framework.py
river_core/templates/setup/reference/sample_plugin.py
river_core-1.9.7.dist-info/LICENSE.incore
river_core-1.9.7.dist-info/LICENSE.tessolve
river_core-1.9.7.dist-info/METADATA
river_core-1.9.7.dist-info/WHEEL
river_core-1.9.7.dist-info/entry_points.txt
river_core-1.9.7.dist-info/top_level.txt
river_core-1.9.7.dist-info/RECORD
