Metadata-Version: 2.1
Name: river-core
Version: 1.9.7
Summary: RiVer Core Verification Framework
Home-page: https://github.com/incoresemi/river_core
Author: InCore Semiconductors Pvt. Ltd.; Tessolve
Author-email: neelgala@incoresemi.com
License: BSD-3-Clause
Keywords: river_core
Classifier: Development Status :: 3 - Alpha
Classifier: Intended Audience :: Developers
Classifier: License :: OSI Approved :: BSD License
Classifier: Natural Language :: English
Classifier: Programming Language :: Python :: 3
Classifier: Programming Language :: Python :: 3.6
Classifier: Programming Language :: Python :: 3.7
Classifier: Programming Language :: Python :: 3.8
Requires-Python: >=3.6
License-File: LICENSE.incore
License-File: LICENSE.tessolve
Requires-Dist: click>=7.0
Requires-Dist: ruamel.yaml>=0.16.0
Requires-Dist: envyaml
Requires-Dist: pytest
Requires-Dist: pytest-runner
Requires-Dist: pytest-timeout
Requires-Dist: pytest-xdist
Requires-Dist: pytest-reportlog
Requires-Dist: pytest-html
Requires-Dist: colorlog
Requires-Dist: configparser
Requires-Dist: ansi2html
Requires-Dist: Cerberus>=1.3.4
Requires-Dist: lief
